napoleon/__init__.py
napoleon/module.py
napoleon_network-0.1.6.dist-info/LICENSE.txt
napoleon_network-0.1.6.dist-info/METADATA
napoleon_network-0.1.6.dist-info/WHEEL
napoleon_network-0.1.6.dist-info/top_level.txt
napoleon_network-0.1.6.dist-info/RECORD
