Metadata-Version: 2.2
Name: napoleon-network
Version: 0.1.6
Summary: Une librairie pour creer une IA basique
Home-page: https://github.com/MathNosseb/Napoleon
Author: Matheo
Author-email: m.besson2008@gmail.com
License: MIT
Classifier: Programming Language :: Python :: 3
Classifier: License :: OSI Approved :: MIT License
Classifier: Operating System :: OS Independent
Requires-Python: >=3.6
License-File: LICENSE.txt
Dynamic: author
Dynamic: author-email
Dynamic: classifier
Dynamic: home-page
Dynamic: license
Dynamic: requires-python
Dynamic: summary
